Metadata-Version: 1.1
Name: shellstream
Version: 0.0.2.4
Summary: Python program that pipes your terminal to the cloud
Home-page: https://github.com/Bpless/shellstream
Author: Benjamin Plesser
Author-email: benjamin.plesser@gmail.com
License: UNKNOWN
Platform: UNKNOWN
Classifier: Programming Language :: Python
